iterm_pane_spliter/__init__.py
iterm_pane_spliter/__main__.py
iterm_pane_spliter/panes_creator.py
iterm_pane_spliter/terminal_helper.py
iterm_pane_spliter/panes_parser/panes_tree.py
iterm_pane_spliter/panes_parser/parser.py
iterm_pane_spliter/panes_parser/types.py
iterm_pane_spliter/panes_parser/validator.py
iterm_pane_spliter-0.0.3.dist-info/entry_points.txt
iterm_pane_spliter-0.0.3.dist-info/LICENSE
iterm_pane_spliter-0.0.3.dist-info/WHEEL
iterm_pane_spliter-0.0.3.dist-info/METADATA
iterm_pane_spliter-0.0.3.dist-info/RECORD
