Metadata-Version: 2.1
Name: iterm-pane-spliter
Version: 0.0.3
Summary: Split iTerm2 panes from the command line
Author: Raz Luvaton
Requires-Python: >=3.8.1
Classifier: Intended Audience :: Developers
Classifier: License :: OSI Approved :: MIT License
Classifier: Programming Language :: Python :: 3 :: Only
Classifier: Programming Language :: Python :: 3.8
Classifier: Programming Language :: Python :: 3.9
Classifier: Programming Language :: Python :: 3.10
Classifier: Programming Language :: Python :: 3.11
Requires-Dist: iterm2 ~= 2.7
Project-URL: Documentation, https://github.com/rluvaton/iterm-pane-spliter/tree/main/README.md
Project-URL: Source, https://github.com/rluvaton/iterm-pane-spliter
Project-URL: Tracker, https://github.com/rluvaton/iterm-pane-spliter/issues
